3.v
module four_bit_ring_counter (
      input clock,
      input reset,
  output [3:0] q
    );
 
  reg[3:0] a;
 
    always @(posedge clock)
      if (reset)
        a = 4'b0001;
 
      else
        begin
        a <=  a<<1; // Notice the blocking assignment
        a[0]<=a[3];
        end
 
    assign q = a;
 
  endmodule

3tb.v
`timescale 1ns / 1ps
module stimulus;
	// Inputs
	reg clock;
	reg reset;
	// Outputs
  wire[3:0] q;
	// Instantiate the Unit Under Test (UUT)
	four_bit_ring_counter r1 (
      .clock(clock), 
      .reset(reset), 
      .q(q)
	);
 
  always #10 clock = ~clock;
 
	initial begin
		// Initialize Inputs
    clock = 0;  
	reset = 0;
 
	#5 reset = 1;
	#20 reset = 0; 
	#500 $finish;
    end  
 
		initial begin
			$dumpfile("ringcounter.vcd");
			$dumpvars(0,stimulus);
          $monitor($time, " clock=%1b,reset=%1b,q=%4b",clock,reset,q);
		 end
	 endmodule

ringcounter.vcd
$date
	Thu Aug 18 14:46:20 2022
$end
$version
	Icarus Verilog
$end
$timescale
	1ps
$end
$scope module stimulus $end
$var wire 4 ! q [3:0] $end
$var reg 1 " clock $end
$var reg 1 # reset $end
$scope module r1 $end
$var wire 1 " clock $end
$var wire 4 $ q [3:0] $end
$var wire 1 # reset $end
$var reg 4 % a [3:0] $end
$upscope $end
$upscope $end
$enddefinitions $end
#0
$dumpvars
bx %
bx $
0#
0"
bx !
$end
#5000
1#
#10000
b1 !
b1 $
b1 %
1"
#20000
0"
#25000
0#
#30000
b10 !
b10 $
b10 %
1"
#40000
0"
#50000
b100 !
b100 $
b100 %
1"
#60000
0"
#70000
b1000 !
b1000 $
b1000 %
1"
#80000
0"
#90000
b1 !
b1 $
b1 %
1"
#100000
0"
#110000
b10 !
b10 $
b10 %
1"
#120000
0"
#130000
b100 !
b100 $
b100 %
1"
#140000
0"
#150000
b1000 !
b1000 $
b1000 %
1"
#160000
0"
#170000
b1 !
b1 $
b1 %
1"
#180000
0"
#190000
b10 !
b10 $
b10 %
1"
#200000
0"
#210000
b100 !
b100 $
b100 %
1"
#220000
0"
#230000
b1000 !
b1000 $
b1000 %
1"
#240000
0"
#250000
b1 !
b1 $
b1 %
1"
#260000
0"
#270000
b10 !
b10 $
b10 %
1"
#280000
0"
#290000
b100 !
b100 $
b100 %
1"
#300000
0"
#310000
b1000 !
b1000 $
b1000 %
1"
#320000
0"
#330000
b1 !
b1 $
b1 %
1"
#340000
0"
#350000
b10 !
b10 $
b10 %
1"
#360000
0"
#370000
b100 !
b100 $
b100 %
1"
#380000
0"
#390000
b1000 !
b1000 $
b1000 %
1"
#400000
0"
#410000
b1 !
b1 $
b1 %
1"
#420000
0"
#430000
b10 !
b10 $
b10 %
1"
#440000
0"
#450000
b100 !
b100 $
b100 %
1"
#460000
0"
#470000
b1000 !
b1000 $
b1000 %
1"
#480000
0"
#490000
b1 !
b1 $
b1 %
1"
#500000
0"
#510000
b10 !
b10 $
b10 %
1"
